LICENSE
README.md
setup.py
evaics/__init__.py
evaics/exceptions.py
evaics/tools.py
evaics.egg-info/PKG-INFO
evaics.egg-info/SOURCES.txt
evaics.egg-info/dependency_links.txt
evaics.egg-info/requires.txt
evaics.egg-info/top_level.txt
evaics/client/__init__.py
evaics/client/bus.py
evaics/client/cloud.py
evaics/client/http.py
evaics/deploy/__init__.py
evaics/sdk/__init__.py
evaics/sdk/__main__.py